sophy/__init__.py
sophy/sophy.py
sophy_python-0.1.1.dist-info/LICENSE.md
sophy_python-0.1.1.dist-info/METADATA
sophy_python-0.1.1.dist-info/WHEEL
sophy_python-0.1.1.dist-info/top_level.txt
sophy_python-0.1.1.dist-info/RECORD
