Metadata-Version: 2.1
Name: sophy-python
Version: 0.1.1
Summary: A Slack notification utility
Home-page: https://github.com/SidhartK/sophy-python
Author: Sidhart Krishnan
Author-email: Sidhart Krishnan <sidhartkrishnan@gmail.com>
Project-URL: Homepage, https://github.com/yourusername/sophy-python
Project-URL: Repository, https://github.com/yourusername/sophy-python
Classifier: Programming Language :: Python :: 3
Classifier: License :: OSI Approved :: MIT License
Classifier: Operating System :: OS Independent
Requires-Python: >=3.6
License-File: LICENSE.md
Requires-Dist: requests>=2.25.1
Provides-Extra: dev
Requires-Dist: pytest; extra == "dev"
Requires-Dist: twine; extra == "dev"
Requires-Dist: build; extra == "dev"
